llama_index_cmem/__init__.py
llama_index_cmem/default_prompts.py
llama_index_cmem/executor/__init__.py
llama_index_cmem/executor/cmem_sparql_executor.py
llama_index_cmem/executor/sparql_executor.py
llama_index_cmem/executor/sparql_query_handler.py
llama_index_cmem/readers/__init__.py
llama_index_cmem/readers/sparql_reader.py
llama_index_cmem/retrievers/__init__.py
llama_index_cmem/retrievers/cmem_query_catalog_retriever.py
llama_index_cmem/retrievers/sparql_retriever.py
llama_index_cmem-0.6.1.dist-info/LICENSE
llama_index_cmem-0.6.1.dist-info/METADATA
llama_index_cmem-0.6.1.dist-info/WHEEL
llama_index_cmem-0.6.1.dist-info/RECORD
