Metadata-Version: 2.3
Name: llama-index-cmem
Version: 0.6.1
Summary: llama-index tools eccenca Corporate Memory Integration
License: Apache-2.0
Author: eccenca GmbH
Author-email: cmempy-developer@eccenca.com
Requires-Python: >=3.11,<4
Classifier: Development Status :: 4 - Beta
Classifier: License :: OSI Approved :: Apache Software License
Classifier: Programming Language :: Python :: 3
Classifier: Programming Language :: Python :: 3.11
Classifier: Programming Language :: Python :: 3.12
Classifier: Programming Language :: Python :: 3.13
Requires-Dist: cmem-cmempy (>=24.2.0,<25.0.0)
Requires-Dist: ipykernel (>=6.29.5,<7.0.0)
Requires-Dist: llama-index (>=0.12.5,<0.13.0)
Requires-Dist: python-dotenv (>=1.0.1,<2.0.0)
